[
  {
    "total_page_number": 12
  },
  {
    "total_token": 1426
  },
  {
    "toc_content": "2 | Page  \n  \n \n \nContents  \n \nPURPOSE  :   3 \nSCOPE :  3 \nROLES AND RESPONSIBILITY  :  3 \nPRE-REQUISITES :  3 \nPROCEDURE/ Steps  :  :  4 \nDOS  :  :  11 \nDON\u2019TS  :  :  11 \nESCALATIONS  :  11 \nDEPENDENCIES  :  :  11 \nSIGNATURES  :  :   11 \n \n ",
    "toc_page_list": [
      2
    ],
    "page_index_given_in_toc": "yes"
  },
  {
    "message": "toc_with_page_number: [{'structure': '1', 'title': 'PURPOSE', 'page': 3}, {'structure': '2', 'title': 'SCOPE', 'page': 3}, {'structure': '3', 'title': 'ROLES AND RESPONSIBILITY', 'page': 3}, {'structure': '4', 'title': 'PRE-REQUISITES', 'page': 3}, {'structure': '5', 'title': 'PROCEDURE/ Steps', 'page': 4}, {'structure': '6', 'title': 'DOS', 'page': 11}, {'structure': '7', 'title': 'DON\u2019TS', 'page': 11}, {'structure': '8', 'title': 'ESCALATIONS', 'page': 11}, {'structure': '9', 'title': 'DEPENDENCIES', 'page': 11}, {'structure': '10', 'title': 'SIGNATURES', 'page': 11}]"
  },
  {
    "message": "toc_with_physical_index: [{'structure': '1', 'title': 'PURPOSE', 'physical_index': '<physical_index_4>'}, {'structure': '2', 'title': 'SCOPE', 'physical_index': '<physical_index_4>'}, {'structure': '3', 'title': 'ROLES AND RESPONSIBILITY', 'physical_index': '<physical_index_4>'}, {'structure': '4', 'title': 'PRE-REQUISITES', 'physical_index': '<physical_index_4>'}, {'structure': '5', 'title': 'PROCEDURE/ Steps', 'physical_index': '<physical_index_5>'}, {'structure': '6', 'title': 'DOS', 'physical_index': '<physical_index_12>'}, {'structure': '7', 'title': 'DON\u2019TS', 'physical_index': '<physical_index_12>'}, {'structure': '8', 'title': 'ESCALATIONS', 'physical_index': '<physical_index_12>'}, {'structure': '9', 'title': 'DEPENDENCIES', 'physical_index': '<physical_index_12>'}, {'structure': '10', 'title': 'SIGNATURES', 'physical_index': '<physical_index_12>'}]"
  },
  {
    "message": "toc_with_physical_index: [{'structure': '1', 'title': 'PURPOSE', 'physical_index': 4}, {'structure': '2', 'title': 'SCOPE', 'physical_index': 4}, {'structure': '3', 'title': 'ROLES AND RESPONSIBILITY', 'physical_index': 4}, {'structure': '4', 'title': 'PRE-REQUISITES', 'physical_index': 4}, {'structure': '5', 'title': 'PROCEDURE/ Steps', 'physical_index': 5}, {'structure': '6', 'title': 'DOS', 'physical_index': 12}, {'structure': '7', 'title': 'DON\u2019TS', 'physical_index': 12}, {'structure': '8', 'title': 'ESCALATIONS', 'physical_index': 12}, {'structure': '9', 'title': 'DEPENDENCIES', 'physical_index': 12}, {'structure': '10', 'title': 'SIGNATURES', 'physical_index': 12}]"
  },
  {
    "message": "matching_pairs: [{'title': 'PURPOSE', 'page': 3, 'physical_index': 4}, {'title': 'SCOPE', 'page': 3, 'physical_index': 4}, {'title': 'ROLES AND RESPONSIBILITY', 'page': 3, 'physical_index': 4}, {'title': 'PRE-REQUISITES', 'page': 3, 'physical_index': 4}, {'title': 'PROCEDURE/ Steps', 'page': 4, 'physical_index': 5}, {'title': 'DOS', 'page': 11, 'physical_index': 12}, {'title': 'DON\u2019TS', 'page': 11, 'physical_index': 12}, {'title': 'ESCALATIONS', 'page': 11, 'physical_index': 12}, {'title': 'DEPENDENCIES', 'page': 11, 'physical_index': 12}, {'title': 'SIGNATURES', 'page': 11, 'physical_index': 12}]"
  },
  {
    "message": "offset: 1"
  },
  {
    "message": "toc_with_page_number: [{'structure': '1', 'title': 'PURPOSE', 'physical_index': 4}, {'structure': '2', 'title': 'SCOPE', 'physical_index': 4}, {'structure': '3', 'title': 'ROLES AND RESPONSIBILITY', 'physical_index': 4}, {'structure': '4', 'title': 'PRE-REQUISITES', 'physical_index': 4}, {'structure': '5', 'title': 'PROCEDURE/ Steps', 'physical_index': 5}, {'structure': '6', 'title': 'DOS', 'physical_index': 12}, {'structure': '7', 'title': 'DON\u2019TS', 'physical_index': 12}, {'structure': '8', 'title': 'ESCALATIONS', 'physical_index': 12}, {'structure': '9', 'title': 'DEPENDENCIES', 'physical_index': 12}, {'structure': '10', 'title': 'SIGNATURES', 'physical_index': 12}]"
  },
  {
    "message": "toc_with_page_number: [{'structure': '1', 'title': 'PURPOSE', 'physical_index': 4}, {'structure': '2', 'title': 'SCOPE', 'physical_index': 4}, {'structure': '3', 'title': 'ROLES AND RESPONSIBILITY', 'physical_index': 4}, {'structure': '4', 'title': 'PRE-REQUISITES', 'physical_index': 4}, {'structure': '5', 'title': 'PROCEDURE/ Steps', 'physical_index': 5}, {'structure': '6', 'title': 'DOS', 'physical_index': 12}, {'structure': '7', 'title': 'DON\u2019TS', 'physical_index': 12}, {'structure': '8', 'title': 'ESCALATIONS', 'physical_index': 12}, {'structure': '9', 'title': 'DEPENDENCIES', 'physical_index': 12}, {'structure': '10', 'title': 'SIGNATURES', 'physical_index': 12}]"
  },
  {
    "mode": "process_toc_with_page_numbers",
    "accuracy": 1.0,
    "incorrect_results": []
  },
  {
    "message": "Checking title appearance in start concurrently"
  },
  {
    "message": "Response: {'thinking': \"The page_text begins with '3 | Page', followed by 'PURPOSE', 'SCOPE', and 'ROLES AND RESPONSIBILITY' before reaching the 'PRE-REQUISITES' section. Since there is significant content preceding the section title, it does not start at the beginning of the page_text.\", 'start_begin': 'no'}"
  },
  {
    "message": "Response: {'thinking': \"The page_text begins with '11 | Page', followed by whitespace, before reaching the section title 'DOS'. Since there is content (the page number) preceding the section title, the section does not start at the very beginning of the page_text.\", 'start_begin': 'no'}"
  },
  {
    "message": "Response: {'thinking': \"The page_text begins with '3 | Page', followed by the section title 'PURPOSE'. Since '3 | Page' appears before the section title, the section title is not the very first content in the page_text.\", 'start_begin': 'no'}"
  },
  {
    "message": "Response: {'thinking': \"The page_text begins with '11 | Page', followed by 'DOS', and then 'DON\u2019TS'. Since there is content ('11 | Page' and 'DOS') appearing before the section title 'DON\u2019TS', the section does not start at the beginning of the page_text.\", 'start_begin': 'no'}"
  },
  {
    "message": "Response: {'thinking': \"The page_text begins with '0 | Page JUNE 30, 2025 OADA -MASS Input Process FOR <CMHL > .'. The section title 'Preface' does not appear at the beginning of this text, nor does it appear anywhere within the provided content.\", 'start_begin': 'no'}"
  },
  {
    "message": "Response: {'thinking': \"The page_text begins with '11 | Page', followed by 'DOS', 'DON\u2019TS', and then 'ESCALATIONS'. Since there is content (page number, DOS, DON'TS) appearing before the section title 'ESCALATIONS', it does not start at the beginning of the page_text.\", 'start_begin': 'no'}"
  },
  {
    "message": "Response: {'thinking': \"The page_text begins with '3 | Page', followed by 'PURPOSE' and 'SCOPE' sections before reaching 'ROLES AND RESPONSIBILITY'. Since there is content (page number, purpose, and scope) preceding the target section title, it does not start at the beginning of the page_text.\", 'start_begin': 'no'}"
  },
  {
    "message": "Response: {'thinking': \"The page_text begins with '11 | Page', followed by several other section titles ('DOS', 'DON\u2019TS', 'ESCALATIONS', 'DEPENDENCIES') before reaching 'SIGNATURES'. Since 'SIGNATURES' is not the first content in the page_text, it does not start at the beginning.\", 'start_begin': 'no'}"
  },
  {
    "message": "Response: {'thinking': \"The page_text begins with '11 | Page', followed by 'DOS', 'DON\u2019TS', and 'ESCALATIONS' before reaching the 'DEPENDENCIES' section title. Since there is significant content preceding the 'DEPENDENCIES' title, it does not start at the beginning of the page_text.\", 'start_begin': 'no'}"
  },
  {
    "message": "Response: {'thinking': \"The page_text begins with '3 | Page', followed by 'PURPOSE', and then the 'SCOPE' section. Since there is content ('3 | Page' and 'PURPOSE') appearing before the 'SCOPE' title, the section does not start at the beginning of the page_text.\", 'start_begin': 'no'}"
  },
  {
    "message": "Response: {'thinking': \"The page_text begins with '4 | Page', followed by whitespace, before the section title 'PROCEDURE / STEPS' appears. Since there is content ('4 | Page') preceding the section title, the section does not start at the very beginning of the page_text.\", 'start_begin': 'no'}"
  }
]